[{"accel":[0.0,0.0,0.0],"debugColour":[1.0,1.0,1.0],"diffuseColour":[1.0,1.0,1.0],"friendlyName":"sphere","inverseMass":0.0,"isVisible":true,"isWireframe":false,"meshName":"sphereMesh","objectColourRGBA":[0.0,1.0,0.0],"physicsShapeType":4,"positionXYZ":[0.0,10.0,0.0],"rotationXYZ":[0.0,0.0,0.0],"scale":2.0,"specularColour":[1.0,1.0,1.0],"velocity":[0.0,0.0,0.0]},{"accel":[0.0,0.0,0.0],"debugColour":[1.0,1.0,1.0],"diffuseColour":[1.0,1.0,1.0],"friendlyName":"sphere2","inverseMass":0.0,"isVisible":true,"isWireframe":false,"meshName":"sphereMesh","objectColourRGBA":[0.0,1.0,0.0],"physicsShapeType":4,"positionXYZ":[10.0,10.0,0.0],"rotationXYZ":[0.0,0.0,0.0],"scale":4.0,"specularColour":[1.0,1.0,1.0],"velocity":[0.0,0.0,0.0]}]